pyzeebe/__init__.py
pyzeebe/channel/__init__.py
pyzeebe/channel/camunda_cloud_channel.py
pyzeebe/channel/channel_options.py
pyzeebe/channel/insecure_channel.py
pyzeebe/channel/secure_channel.py
pyzeebe/channel/utils.py
pyzeebe/client/__init__.py
pyzeebe/client/client.py
pyzeebe/client/sync_client.py
pyzeebe/errors/__init__.py
pyzeebe/errors/credentials_errors.py
pyzeebe/errors/job_errors.py
pyzeebe/errors/message_errors.py
pyzeebe/errors/process_errors.py
pyzeebe/errors/pyzeebe_errors.py
pyzeebe/errors/zeebe_errors.py
pyzeebe/function_tools/__init__.py
pyzeebe/function_tools/async_tools.py
pyzeebe/function_tools/dict_tools.py
pyzeebe/function_tools/parameter_tools.py
pyzeebe/grpc_internals/__init__.py
pyzeebe/grpc_internals/grpc_utils.py
pyzeebe/grpc_internals/zeebe_adapter.py
pyzeebe/grpc_internals/zeebe_adapter_base.py
pyzeebe/grpc_internals/zeebe_job_adapter.py
pyzeebe/grpc_internals/zeebe_message_adapter.py
pyzeebe/grpc_internals/zeebe_process_adapter.py
pyzeebe/job/__init__.py
pyzeebe/job/job.py
pyzeebe/job/job_status.py
pyzeebe/task/__init__.py
pyzeebe/task/exception_handler.py
pyzeebe/task/task.py
pyzeebe/task/task_builder.py
pyzeebe/task/task_config.py
pyzeebe/task/types.py
pyzeebe/worker/__init__.py
pyzeebe/worker/job_executor.py
pyzeebe/worker/job_poller.py
pyzeebe/worker/task_router.py
pyzeebe/worker/task_state.py
pyzeebe/worker/worker.py
pyzeebe_fork-1.1.dist-info/LICENSE.md
pyzeebe_fork-1.1.dist-info/WHEEL
pyzeebe_fork-1.1.dist-info/METADATA
pyzeebe_fork-1.1.dist-info/RECORD
