Metadata-Version: 2.1
Name: pyzeebe-fork
Version: 1.1
Summary: Zeebe client api
Home-page: https://github.com/WhatsLab/pyzebee
License: MIT
Keywords: zeebe,workflow,workflow-engine
Author: Mohamed
Author-email: mohamed.shahin@nana.sa
Requires-Python: >=3.6,<4.0
Classifier: License :: OSI Approved :: MIT License
Classifier: Operating System :: OS Independent
Classifier: Programming Language :: Python :: 3
Classifier: Programming Language :: Python :: 3.6
Classifier: Programming Language :: Python :: 3.7
Classifier: Programming Language :: Python :: 3.8
Classifier: Programming Language :: Python :: 3.9
Classifier: Programming Language :: Python :: 3.10
Classifier: Programming Language :: Python :: 3
Requires-Dist: aiofiles (>=0.7,<0.9)
Requires-Dist: oauthlib (>=3.1.0,<3.2.0)
Requires-Dist: requests-oauthlib (>=1.3.0,<1.4.0)
Requires-Dist: zeebe-grpc (>=1.2.0,<2.0.0)
Project-URL: Documentation, https://pyzeebe.readthedocs.io/en/latest
Project-URL: Repository, https://github.com/WhatsLab/pyzebee
